Workbook

Sheet ReadMe
A1: Hindustan Unilever Limited – Financial Analysis Dashboard
A3: Company | B3: Hindustan Unilever Limited (HUL)
A4: Analysis Period | B4: FY2020-21 to FY2024-25
A5: Financial Basis | B5: Standalone Financial Statements
A6: Currency | B6: ₹ Crore
A7: Tool | B7: Microsoft Excel
A8: Data Sources | B8: HUL Annual Reports & Historical Financial Performance
A9: Purpose | B9: Analyse HUL's growth, profitability, returns, leverage and working-capital efficiency
A11: Methodology Section | D11: Key Metrics Section
A12: • Revenue, EBITDA and PAT growth calculated using YoY growth rates. | E12: Revenue Growth
A13: • EBITDA Margin = EBITDA / Revenue. | E13: EBITDA Growth
A14: • PAT Margin = PAT / Revenue. | E14: PAT Growth
A15: • ROE = PAT / Average Shareholders' Equity. | E15: EBITDA & PAT Margin
A16: • Net Working Capital = Current Assets - Current Liabilities. | E16: ROE & ROCE
A17: • Debt-to-Equity uses lease liabilities as HUL has no conventional borrowings. | E17: Debt-to-Equity
A18: • ROCE uses HUL's reported methodology. | E18: Net Working Capital
E19: Working Capital Days
A20: Assumptions / Notes | E20: Cash Conversion Cycle
A21: FY2020-21 is the starting year of the analysis. Therefore, YoY growth and average-equity based ROE requiring earlier-year information are not calculated where prior-year data falls outside the selected period. | E21: Revenue / EBITDA / PAT CAGR

Sheet Raw Data
A1: HUL Financial Analysis – Raw Data
A3: Particulars (₹ Cr) | B3: Fy 2020-21 | C3: Fy 2021-22 | D3: Fy 2022-23 | E3: Fy 2023-24 | F3: Fy 2024-25 | G3: SOURCE
A4: Turnover | B4: 45311 | C4: 50336 | D4: 58154 | E4: 59579 | F4: 60680 | G4: HUL Historical Data
A5: EBITDA | B5: 11324 | C5: 12503 | D5: 13632 | E5: 14190 | F5: 14289 | G5: HUL Historical Data
A6: PAT | B6: 7954 | C6: 8818 | D6: 9962 | E6: 10114 | F6: 10644 | G6: HUL Historical Data
A7: Cash From Operations | B7: 11324 | C7: 11684 | D7: 12694 | E7: 15179 | F7: 13789 | G7: HUL Historical Data
A9: Total Assets | B9: 68116 | C9: 69737 | D9: 71825 | E9: 77076 | F9: 78313 | G9: HUL Annual Report
A10: Total Equity | B10: 47434 | C10: 48760 | D10: 50221 | E10: 50973 | F10: 49153 | G10: HUL Annual Report
A11: Current Assets | B11: 13640 | C11: 14647 | D11: 16049 | E11: 20296 | F11: 20899 | G11: HUL Annual Report
A12: Current Liabilities | B12: 10841 | C12: 10944 | D12: 11627 | E12: 12403 | F12: 15672 | G12: HUL Annual Report
A13: Inventory | B13: 3383 | C13: 3890 | D13: 4031 | E13: 3812 | F13: 4161 | G13: HUL Annual Report
A14: Trade Receivables | B14: 1648 | C14: 1932 | D14: 2735 | E14: 2690 | F14: 3450 | G14: HUL Annual Report
A15: Trade Payables | B15: 8627 | C15: 8864 | D15: 9391 | E15: 10148 | F15: 10998 | G15: HUL Annual Report
A16: Cash & Cash Equivalents | B16: 1740 | C16: 988 | D16: 586 | E16: 609 | F16: 5947 | G16: HUL Annual Report
... A18: Current Lease Liability | B18: 264 | C18: 285 | D18: 293 | E18: 340 | F18: 380 | G18: HUL Annual Report

Sheet Ratios
A1: HUL Financial Ratio Analysis
A3: Particulars | B3: FY2020-21 | C3: FY2021-22 | D3: FY2022-23 | E3: FY2023-24 | F3: FY2024-25
A4: Revenue YoY Growth | B4: N\A | C4: =('Raw Data'!C4/'Raw Data'!B4)-1 -> 0.11090022 | D4: =('Raw Data'!D4/'Raw Data'!C4)-1 -> 0.15531627 | E4: =('Raw Data'!E4/'Raw Data'!D4)-1 -> 0.024503903 | F4: =('Raw Data'!F4/'Raw Data'!E4)-1 -> 0.018479666
A5: EBITDA YoY Growth | B5: N\A | C5: =('Raw Data'!C5/'Raw Data'!B5)-1 -> 0.10411515 | D5: =('Raw Data'!D5/'Raw Data'!C5)-1 -> 0.090298328 | E5: =('Raw Data'!E5/'Raw Data'!D5)-1 -> 0.040933099 | F5: =('Raw Data'!F5/'Raw Data'!E5)-1 -> 0.0069767442
A6: PAT YoY Growth | B6: N\A | C6: =('Raw Data'!C6/'Raw Data'!B6)-1 -> 0.10862459 | D6: =('Raw Data'!D6/'Raw Data'!C6)-1 -> 0.12973463 | E6: =('Raw Data'!E6/'Raw Data'!D6)-1 -> 0.01525798 | F6: =('Raw Data'!F6/'Raw Data'!E6)-1 -> 0.05240261
A8: EBITDA Margin | B8: ='Raw Data'!B5/'Raw Data'!B4 -> 0.24991724 | C8: ='Raw Data'!C5/'Raw Data'!C4 -> 0.24839081 | D8: ='Raw Data'!D5/'Raw Data'!D4 -> 0.23441208 | E8: ='Raw Data'!E5/'Raw Data'!E4 -> 0.23817117 | F8: ='Raw Data'!F5/'Raw Data'!F4 -> 0.23548121
A9: PAT Margin | B9: ='Raw Data'!B6/'Raw Data'!B4 -> 0.17554236 | C9: ='Raw Data'!C6/'Raw Data'!C4 -> 0.17518277 | D9: ='Raw Data'!D6/'Raw Data'!D4 -> 0.17130378 | E9: ='Raw Data'!E6/'Raw Data'!E4 -> 0.1697578 | F9: ='Raw Data'!F6/'Raw Data'!F4 -> 0.175412
A11: Net Working Capital | B11: ='Raw Data'!B11-'Raw Data'!B12 -> 2799 | C11: ='Raw Data'!C11-'Raw Data'!C12 -> 3703 | D11: ='Raw Data'!D11-'Raw Data'!D12 -> 4422 | E11: ='Raw Data'!E11-'Raw Data'!E12 -> 7893 | F11: ='Raw Data'!F11-'Raw Data'!F12 -> 5227
A12: ROE | C12: ='Raw Data'!C6/AVERAGE('Raw Data'!B10,'Raw Data'!C10) -> 0.18333784 | D12: ='Raw Data'!D6/AVERAGE('Raw Data'!C10,'Raw Data'!D10) -> 0.20129116 | E12: ='Raw Data'!E6/AVERAGE('Raw Data'!D10,'Raw Data'!E10) -> 0.19989327 | F12: ='Raw Data'!F6/AVERAGE('Raw Data'!E10,'Raw Data'!F10) -> 0.21261211
A14: Lease Liabilities | B14: ='Raw Data'!B17+'Raw Data'!B18 -> 943 | C14: ='Raw Data'!C17+'Raw Data'!C18 -> 971 | D14: ='Raw Data'!D17+'Raw Data'!D18 -> 1039 | E14: ='Raw Data'!E17+'Raw Data'!E18 -> 1374 | F14: ='Raw Data'!F17+'Raw Data'!F18 -> 1537
A15: Debt to Equity | B15: =B14/'Raw Data'!B10 -> 0.019880255 | C15: =C14/'Raw Data'!C10 -> 0.019913864 | D15: =D14/'Raw Data'!D10 -> 0.020688557 | E15: =E14/'Raw Data'!E10 -> 0.026955447 | F15: =F14/'Raw Data'!F10 -> 0.031269709
A16: ROCE (Reported) | B16: 1.13 | C16: 1.078 | D16: 1.019 | E16: 0.963 | F16: 1.082
A18: Inventory Turnover | B18: 14 | C18: 13.8 | D18: 14.7 | E18: 15.2 | F18: 15.2
A19: Receivable Turnover | B19: 30.2 | C19: 28.1 | D19: 24.9 | E19: 22 | F19: 19.8
A20: Payable Turnover | B20: 4 | C20: 4.1 | D20: 4.7 | E20: 4.3 | F20: 4.4
A22: Inventory Days | B22: =365/B18 -> 26.071429 | C22: =365/C18 -> 26.449275 | D22: =365/D18 -> 24.829932 | E22: =365/E18 -> 24.013158 | F22: =365/F18 -> 24.013158
A23: Receivable Days | B23: =365/B19 -> 12.086093 | C23: =365/C19 -> 12.989324 | D23: =365/D19 -> 14.658635 | E23: =365/E19 -> 16.590909 | F23: =365/F19 -> 18.434343
A24: payable Days | B24: =365/B20 -> 91.25 | C24: =365/C20 -> 89.02439 | D24: =365/D20 -> 77.659574 | E24: =365/E20 -> 84.883721 | F24: =365/F20 -> 82.954545
A25: Cash Conversion Cycle | B25: =B22+B23-B24 -> -53.092479 | C25: =C22+C23-C24 -> -49.585791 | D25: =D22+D23-D24 -> -38.171008 | E25: =E22+E23-E24 -> -44.279654 | F25: =F22+F23-F24 -> -40.507044
A27: Revenue CAGR | B27: =('Raw Data'!F4/'Raw Data'!B4)^(1/4)-1 -> 0.075747836
A28: EBITDA CAGR | B28: =('Raw Data'!F5/'Raw Data'!B5)^(1/4)-1 -> 0.059864861
A29: PAT CAGR | B29: =('Raw Data'!F6/'Raw Data'!B6)^(1/4)-1 -> 0.075548056

Sheet Dashboard
A1: Hindustan Unilever Limited
A2: 5-Year Financial Performance Dashboard | FY2020-21 to FY2024-25
B4: Revenue | E4: EBITDA Margin | H4: PAT | K4: ROCE
B5: =TEXT('Raw Data'!F4,"₹#,##0")&" Cr" -> ₹60,680 Cr | E5: =Ratios!F8 -> 0.23548121 | H5: =TEXT('Raw Data'!F6,"₹#,##0")&" Cr" -> ₹10,644 Cr | K5: =Ratios!F16 -> 1.082
A34: Key Takeways
B36: Growth | F36: Profitability | J36: Efficiency
B37: Revenue CAGR: 7.57% FY25 revenue growth slowed to 1.85% | F37: FY25 EBITDA Margin: 23.55% Margin declined from ~25.0% in FY21. | J37: FY25 CCC: -40.5 Days Negative CCC reflects strong working-capital efficiency.

Sheet Insights
A1: HUL Financial Analysis – Key Insights
A3: Theme | B3: Observation | C3: Evidence | D3: Business Interpretation
A4: Growth | B4: Revenue grew steadily over the 5-year period, but recent growth has slowed. | C4: Revenue CAGR 7.57%; FY25 YoY growth only 1.85%. | D4: HUL has delivered long-term growth, but near-term topline momentum has moderated.
A5: Profitability | B5: EBITDA growth lagged revenue growth over the period. | C5: Revenue CAGR 7.57% vs EBITDA CAGR 5.99%; EBITDA margin fell from about 25.0% to 23.5%. | D5: This indicates some operating margin pressure despite revenue expansion.
A6: Net Profit | B6: PAT remained comparatively resilient. | C6: PAT CAGR 7.55% and PAT margin improved from 16.98% in FY24 to 17.54% in FY25. | D6: Bottom-line profitability recovered even though operating margin remained under pressure.
A7: Return on Capital | B7: ROCE weakened until FY24 but recovered strongly in FY25 | C7: ROCE: 113.0% → 107.8% → 101.9% → 96.3% → 108.2%. | D7: Capital efficiency remains very strong, with a notable recovery in the latest year.
A8: Working Capital | B8: HUL maintained a negative cash conversion cycle. | C8: CCC remained negative; FY25 approximately -40.5 days. | D8: A negative CCC indicates that HUL generally converts its operating cycle into cash before supplier payments become due, supporting efficient working-capital management.
A9: Leverage | B9: HUL operates with very low financial leverage. | C9: No conventional borrowings; Debt/Equity approximately 0.03x in FY25 using lease liabilities. | D9: Low leverage reduces financing risk and gives HUL a conservative balance-sheet position.
