Workbook

Sheet ReadMe
A15: Hindustan Uniliver Limited (HUL)
A17: Company | B17: Hindustan Unilever Limited (HUL)
A18: Analysis Period | B18: FY2020-21 to FY2024-25
A19: Financial Basis | B19: Standalone Financial Statements
A20: Currency | B20: ₹ Crore
A21: Tool | B21: Microsoft Excel
A22: Data Sources | B22: HUL Annual Reports & Historical Financial Performance
A23: Purpose | B23: Analyse HUL's growth, profitability, returns, leverage and working-capital efficiency
A25: Methodology Section | D25: Key Metrics Section
A26: • Revenue, EBITDA and PAT growth calculated using YoY growth rates. | E26: Revenue Growth
A27: • EBITDA Margin = EBITDA / Revenue. | E27: EBITDA Growth
A28: • PAT Margin = PAT / Revenue. | E28: PAT Growth
A29: • ROE = PAT / Average Shareholders' Equity. | E29: EBITDA & PAT Margin
A30: • Net Working Capital = Current Assets - Current Liabilities. | E30: ROE & ROCE
A31: • Debt-to-Equity uses lease liabilities as HUL has no conventional borrowings. | E31: Debt-to-Equity
A32: • ROCE uses HUL's reported methodology. | E32: Net Working Capital
E33: Working Capital Days
A34: Assumptions / Notes | E34: Cash Conversion Cycle
A35: FY2020-21 is the starting year of the analysis. Therefore, YoY growth and average-equity based ROE requiring earlier-year information are not calculated where prior-year data falls outside the selected period. | E35: Revenue / EBITDA / PAT CAGR
A40: Advanced Analysis Module | D40: Excel Technique Used
A41: Common-Size & Trend Analysis | D41: Financial Ratio Analysis
A42: DuPont ROE Analysis | D42: Charts & Dashboard
A43: Bear / Base / Bull Scenario Forecasting | D43: Scenario Analysis
A44: P/E & EV/EBITDA Valuation | D44: Sensitivity Analysis
A45: Valuation Sensitivity Analysis | D45: Linked Cell Formulas

Sheet Raw Data
A1: HUL Financial Analysis – Raw Data
A3: Particulars (₹ Cr) | B3: Fy 2020-21 | C3: Fy 2021-22 | D3: Fy 2022-23 | E3: Fy 2023-24 | F3: Fy 2024-25 | G3: SOURCE
A4: Turnover | B4: 45311 | C4: 50336 | D4: 58154 | E4: 59579 | F4: 60680 | G4: HUL Historical Data
A5: EBITDA | B5: 11324 | C5: 12503 | D5: 13632 | E5: 14190 | F5: 14289 | G5: HUL Historical Data
A6: PAT | B6: 7954 | C6: 8818 | D6: 9962 | E6: 10114 | F6: 10644 | G6: HUL Historical Data
A7: Cash From Operations | B7: 11324 | C7: 11684 | D7: 12694 | E7: 15179 | F7: 13789 | G7: HUL Historical Data
A9: Total Assets | B9: 68116 | C9: 69737 | D9: 71825 | E9: 77076 | F9: 78313 | G9: HUL Annual Report
A10: Total Equity | B10: 47434 | C10: 48760 | D10: 50221 | E10: 50973 | F10: 49153 | G10: HUL Annual Report
A11: Current Assets | B11: 13640 | C11: 14647 | D11: 16049 | E11: 20296 | F11: 20899 | G11: HUL Annual Report
A12: Current Liabilities | B12: 10841 | C12: 10944 | D12: 11627 | E12: 12403 | F12: 15672 | G12: HUL Annual Report
A13: Inventory | B13: 3383 | C13: 3890 | D13: 4031 | E13: 3812 | F13: 4161 | G13: HUL Annual Report
A14: Trade Receivables | B14: 1648 | C14: 1932 | D14: 2735 | E14: 2690 | F14: 3450 | G14: HUL Annual Report
A15: Trade Payables | B15: 8627 | C15: 8864 | D15: 9391 | E15: 10148 | F15: 10998 | G15: HUL Annual Report
A16: Cash & Cash Equivalents | B16: 1740 | C16: 988 | D16: 586 | E16: 609 | F16: 5947 | G16: HUL Annual Report
... A18: Current Lease Liability | B18: 264 | C18: 285 | D18: 293 | E18: 340 | F18: 380 | G18: HUL Annual Report

Sheet Ratios
A1: HUL Financial Ratio Analysis
A3: Particulars | B3: FY2020-21 | C3: FY2021-22 | D3: FY2022-23 | E3: FY2023-24 | F3: FY2024-25
A4: Revenue YoY Growth | B4: N\A | C4: =('Raw Data'!C4/'Raw Data'!B4)-1 -> 0.11090022 | D4: =('Raw Data'!D4/'Raw Data'!C4)-1 -> 0.15531627 | E4: =('Raw Data'!E4/'Raw Data'!D4)-1 -> 0.024503903 | F4: =('Raw Data'!F4/'Raw Data'!E4)-1 -> 0.018479666
A5: EBITDA YoY Growth | B5: N\A | C5: =('Raw Data'!C5/'Raw Data'!B5)-1 -> 0.10411515 | D5: =('Raw Data'!D5/'Raw Data'!C5)-1 -> 0.090298328 | E5: =('Raw Data'!E5/'Raw Data'!D5)-1 -> 0.040933099 | F5: =('Raw Data'!F5/'Raw Data'!E5)-1 -> 0.0069767442
A6: PAT YoY Growth | B6: N\A | C6: =('Raw Data'!C6/'Raw Data'!B6)-1 -> 0.10862459 | D6: =('Raw Data'!D6/'Raw Data'!C6)-1 -> 0.12973463 | E6: =('Raw Data'!E6/'Raw Data'!D6)-1 -> 0.01525798 | F6: =('Raw Data'!F6/'Raw Data'!E6)-1 -> 0.05240261
A8: EBITDA Margin | B8: ='Raw Data'!B5/'Raw Data'!B4 -> 0.24991724 | C8: ='Raw Data'!C5/'Raw Data'!C4 -> 0.24839081 | D8: ='Raw Data'!D5/'Raw Data'!D4 -> 0.23441208 | E8: ='Raw Data'!E5/'Raw Data'!E4 -> 0.23817117 | F8: ='Raw Data'!F5/'Raw Data'!F4 -> 0.23548121
A9: PAT Margin | B9: ='Raw Data'!B6/'Raw Data'!B4 -> 0.17554236 | C9: ='Raw Data'!C6/'Raw Data'!C4 -> 0.17518277 | D9: ='Raw Data'!D6/'Raw Data'!D4 -> 0.17130378 | E9: ='Raw Data'!E6/'Raw Data'!E4 -> 0.1697578 | F9: ='Raw Data'!F6/'Raw Data'!F4 -> 0.175412
A11: Net Working Capital | B11: ='Raw Data'!B11-'Raw Data'!B12 -> 2799 | C11: ='Raw Data'!C11-'Raw Data'!C12 -> 3703 | D11: ='Raw Data'!D11-'Raw Data'!D12 -> 4422 | E11: ='Raw Data'!E11-'Raw Data'!E12 -> 7893 | F11: ='Raw Data'!F11-'Raw Data'!F12 -> 5227
A12: ROE | C12: ='Raw Data'!C6/AVERAGE('Raw Data'!B10,'Raw Data'!C10) -> 0.18333784 | D12: ='Raw Data'!D6/AVERAGE('Raw Data'!C10,'Raw Data'!D10) -> 0.20129116 | E12: ='Raw Data'!E6/AVERAGE('Raw Data'!D10,'Raw Data'!E10) -> 0.19989327 | F12: ='Raw Data'!F6/AVERAGE('Raw Data'!E10,'Raw Data'!F10) -> 0.21261211
A14: Lease Liabilities | B14: ='Raw Data'!B17+'Raw Data'!B18 -> 943 | C14: ='Raw Data'!C17+'Raw Data'!C18 -> 971 | D14: ='Raw Data'!D17+'Raw Data'!D18 -> 1039 | E14: ='Raw Data'!E17+'Raw Data'!E18 -> 1374 | F14: ='Raw Data'!F17+'Raw Data'!F18 -> 1537
A15: Debt to Equity | B15: =B14/'Raw Data'!B10 -> 0.019880255 | C15: =C14/'Raw Data'!C10 -> 0.019913864 | D15: =D14/'Raw Data'!D10 -> 0.020688557 | E15: =E14/'Raw Data'!E10 -> 0.026955447 | F15: =F14/'Raw Data'!F10 -> 0.031269709
A16: ROCE (Reported) | B16: 1.13 | C16: 1.078 | D16: 1.019 | E16: 0.963 | F16: 1.082
A18: Inventory Turnover | B18: ='Raw Data'!B4/'Raw Data'!B13 -> 13.393733 | C18: ='Raw Data'!C4/AVERAGE('Raw Data'!B13,'Raw Data'!C13) -> 13.841881 | D18: ='Raw Data'!D4/AVERAGE('Raw Data'!C13,'Raw Data'!D13) -> 14.6835 | E18: ='Raw Data'!E4/AVERAGE('Raw Data'!D13,'Raw Data'!E13) -> 15.192911 | F18: ='Raw Data'!F4/AVERAGE('Raw Data'!E13,'Raw Data'!F13) -> 15.221372
A19: Receivable Turnover | B19: ='Raw Data'!B4/'Raw Data'!B14 -> 27.494539 | C19: ='Raw Data'!C4/AVERAGE('Raw Data'!B14,'Raw Data'!C14) -> 28.12067 | D19: ='Raw Data'!D4/AVERAGE('Raw Data'!C14,'Raw Data'!D14) -> 24.921363 | E19: ='Raw Data'!E4/AVERAGE('Raw Data'!D14,'Raw Data'!E14) -> 21.964608 | F19: ='Raw Data'!F4/AVERAGE('Raw Data'!E14,'Raw Data'!F14) -> 19.765472
A20: Payable Turnover | B20: 4 | C20: 4.1 | D20: 4.7 | E20: 4.3 | F20: 4.4
A22: Inventory Days | B22: =365/B18 -> 27.25155 | C22: =365/C18 -> 26.369249 | D22: =365/D18 -> 24.857834 | E22: =365/E18 -> 24.024363 | F22: =365/F18 -> 23.979441
A23: Receivable Days | B23: =365/B19 -> 13.275364 | C23: =365/C19 -> 12.979776 | D23: =365/D19 -> 14.646069 | E23: =365/E19 -> 16.617642 | F23: =365/F19 -> 18.466546
A24: Payable Days | B24: =365/B20 -> 91.25 | C24: =365/C20 -> 89.02439 | D24: =365/D20 -> 77.659574 | E24: =365/E20 -> 84.883721 | F24: =365/F20 -> 82.954545
A25: Cash Conversion Cycle | B25: =B22+B23-B24 -> -50.723086 | C25: =C22+C23-C24 -> -49.675366 | D25: =D22+D23-D24 -> -38.155671 | E25: =E22+E23-E24 -> -44.241716 | F25: =F22+F23-F24 -> -40.508558
A27: Revenue CAGR | B27: =('Raw Data'!F4/'Raw Data'!B4)^(1/4)-1 -> 0.075747836
A28: EBITDA CAGR | B28: =('Raw Data'!F5/'Raw Data'!B5)^(1/4)-1 -> 0.059864861
A29: PAT CAGR | B29: =('Raw Data'!F6/'Raw Data'!B6)^(1/4)-1 -> 0.075548056

Sheet Common Size and Trend
A1: HUL Common-Size & Trend Analysis
A3: Metric | B3: FY2020-21 | C3: FY2021-22 | D3: FY2022-23 | E3: FY2023-24 | F3: FY2024-25
A5: Revenue Index | B5: ='Raw Data'!B4/'Raw Data'!$B$4*100 -> 100 | C5: ='Raw Data'!C4/'Raw Data'!$B$4*100 -> 111.09002 | D5: ='Raw Data'!D4/'Raw Data'!$B$4*100 -> 128.34411 | E5: ='Raw Data'!E4/'Raw Data'!$B$4*100 -> 131.48904 | F5: ='Raw Data'!F4/'Raw Data'!$B$4*100 -> 133.91892
A6: EBITDA Index | B6: ='Raw Data'!B5/'Raw Data'!$B$5*100 -> 100 | C6: ='Raw Data'!C5/'Raw Data'!$B$5*100 -> 110.41152 | D6: ='Raw Data'!D5/'Raw Data'!$B$5*100 -> 120.38149 | E6: ='Raw Data'!E5/'Raw Data'!$B$5*100 -> 125.30908 | F6: ='Raw Data'!F5/'Raw Data'!$B$5*100 -> 126.18333
A7: PAT Index | B7: ='Raw Data'!B6/'Raw Data'!$B$6*100 -> 100 | C7: ='Raw Data'!C6/'Raw Data'!$B$6*100 -> 110.86246 | D7: ='Raw Data'!D6/'Raw Data'!$B$6*100 -> 125.24516 | E7: ='Raw Data'!E6/'Raw Data'!$B$6*100 -> 127.15615 | F7: ='Raw Data'!F6/'Raw Data'!$B$6*100 -> 133.81946
A8: CFO Index | B8: ='Raw Data'!B7/'Raw Data'!$B$7*100 -> 100 | C8: ='Raw Data'!C7/'Raw Data'!$B$7*100 -> 103.17909 | D8: ='Raw Data'!D7/'Raw Data'!$B$7*100 -> 112.0982 | E8: ='Raw Data'!E7/'Raw Data'!$B$7*100 -> 134.04274 | F8: ='Raw Data'!F7/'Raw Data'!$B$7*100 -> 121.76793
A10: EBITDA as % of Revenue | B10: ='Raw Data'!B5/'Raw Data'!B4 -> 0.24991724 | C10: ='Raw Data'!C5/'Raw Data'!C4 -> 0.24839081 | D10: ='Raw Data'!D5/'Raw Data'!D4 -> 0.23441208 | E10: ='Raw Data'!E5/'Raw Data'!E4 -> 0.23817117 | F10: ='Raw Data'!F5/'Raw Data'!F4 -> 0.23548121
A11: PAT as % of Revenue | B11: ='Raw Data'!B6/'Raw Data'!B4 -> 0.17554236 | C11: ='Raw Data'!C6/'Raw Data'!C4 -> 0.17518277 | D11: ='Raw Data'!D6/'Raw Data'!D4 -> 0.17130378 | E11: ='Raw Data'!E6/'Raw Data'!E4 -> 0.1697578 | F11: ='Raw Data'!F6/'Raw Data'!F4 -> 0.175412
A12: CFO as % of Revenue | B12: ='Raw Data'!B7/'Raw Data'!B4 -> 0.24991724 | C12: ='Raw Data'!C7/'Raw Data'!C4 -> 0.23212015 | D12: ='Raw Data'!D7/'Raw Data'!D4 -> 0.21828249 | E12: ='Raw Data'!E7/'Raw Data'!E4 -> 0.25477098 | F12: ='Raw Data'!F7/'Raw Data'!F4 -> 0.22724127
A14: Current Assets as % of Total Assets | B14: ='Raw Data'!B11/'Raw Data'!B9 -> 0.20024664 | C14: ='Raw Data'!C11/'Raw Data'!C9 -> 0.21003198 | D14: ='Raw Data'!D11/'Raw Data'!D9 -> 0.22344588 | E14: ='Raw Data'!E11/'Raw Data'!E9 -> 0.26332451 | F14: ='Raw Data'!F11/'Raw Data'!F9 -> 0.26686502
A15: Current Liabilities as % of Total Assets | B15: ='Raw Data'!B12/'Raw Data'!B9 -> 0.15915497 | C15: ='Raw Data'!C12/'Raw Data'!C9 -> 0.15693247 | D15: ='Raw Data'!D12/'Raw Data'!D9 -> 0.16187957 | E15: ='Raw Data'!E12/'Raw Data'!E9 -> 0.16091909 | F15: ='Raw Data'!F12/'Raw Data'!F9 -> 0.20012003
A16: Cash as % of Total Assets | B16: ='Raw Data'!B16/'Raw Data'!B9 -> 0.025544659 | C16: ='Raw Data'!C16/'Raw Data'!C9 -> 0.014167515 | D16: ='Raw Data'!D16/'Raw Data'!D9 -> 0.0081587191 | E16: ='Raw Data'!E16/'Raw Data'!E9 -> 0.0079012922 | F16: ='Raw Data'!F16/'Raw Data'!F9 -> 0.075938861
A17: Inventory as % of Current Assets | B17: ='Raw Data'!B13/'Raw Data'!B11 -> 0.24802053 | C17: ='Raw Data'!C13/'Raw Data'!C11 -> 0.2655834 | D17: ='Raw Data'!D13/'Raw Data'!D11 -> 0.2511683 | E17: ='Raw Data'!E13/'Raw Data'!E11 -> 0.18782026 | F17: ='Raw Data'!F13/'Raw Data'!F11 -> 0.19910044
A18: Receivables as % of Revenue | B18: ='Raw Data'!B14/'Raw Data'!B4 -> 0.036370859 | C18: ='Raw Data'!C14/'Raw Data'!C4 -> 0.038382072 | D18: ='Raw Data'!D14/'Raw Data'!D4 -> 0.047030299 | E18: ='Raw Data'!E14/'Raw Data'!E4 -> 0.045150137 | F18: ='Raw Data'!F14/'Raw Data'!F4 -> 0.056855636

Sheet DuPont Analysis
A1: HUL DuPont Analysis
A3: Metric | B3: FY2020-21 | C3: FY2021-22 | D3: FY2022-23 | E3: FY2023-24 | F3: FY2024-25
A5: Net Profit Margin | B5: ='Raw Data'!B6/'Raw Data'!B4 -> 0.17554236 | C5: ='Raw Data'!C6/'Raw Data'!C4 -> 0.17518277 | D5: ='Raw Data'!D6/'Raw Data'!D4 -> 0.17130378 | E5: ='Raw Data'!E6/'Raw Data'!E4 -> 0.1697578 | F5: ='Raw Data'!F6/'Raw Data'!F4 -> 0.175412
A6: Asset Turnover | B6: N/A | C6: 0.73 | D6: ='Raw Data'!D4/AVERAGE('Raw Data'!C9,'Raw Data'!D9) -> 0.82160467 | E6: ='Raw Data'!E4/AVERAGE('Raw Data'!D9,'Raw Data'!E9) -> 0.80024983 | F6: ='Raw Data'!F4/AVERAGE('Raw Data'!E9,'Raw Data'!F9) -> 0.78100766
A7: Equity Multiplier | B7: N/A | C7: =AVERAGE('Raw Data'!B9,'Raw Data'!C9)/AVERAGE('Raw Data'!B10,'Raw Data'!C10) -> 1.4330727 | D7: =AVERAGE('Raw Data'!C9,'Raw Data'!D9)/AVERAGE('Raw Data'!C10,'Raw Data'!D10) -> 1.4301937 | E7: =AVERAGE('Raw Data'!D9,'Raw Data'!E9)/AVERAGE('Raw Data'!D10,'Raw Data'!E10) -> 1.471441 | F7: =AVERAGE('Raw Data'!E9,'Raw Data'!F9)/AVERAGE('Raw Data'!E10,'Raw Data'!F10) -> 1.5519346
A8: DuPont ROE | B8: N/A | C8: =C5*C6*C7 -> 0.18326625 | D8: =D5*D6*D7 -> 0.20129116 | E8: =E5*E6*E7 -> 0.19989327 | F8: =F5*F6*F7 -> 0.21261211
A9: Reported ROE | B9: N/A | C9: =Ratios!C12 -> 0.18333784 | D9: =Ratios!D12 -> 0.20129116 | E9: =Ratios!E12 -> 0.19989327 | F9: =Ratios!F12 -> 0.21261211

Sheet Forecast & Scenario
A1: HUL Forecast & Scenario Analysis
A3: Scenario | B3: Revenue Growth | C3: EBITDA Margin | D3: PAT Margin
A4: Bear Case | B4: 0.02 | C4: 0.22 | D4: 0.16
A5: Base Case | B5: 0.05 | C5: 0.24 | D5: 0.175
A6: Bull Case | B6: 0.08 | C6: 0.25 | D6: 0.185
A8: Forecast Metric | B8: FY2024-25 Actual | C8: FY2025-26 | D8: FY2026-27 | E8: FY2027-28
A9: Base Case Forecast
A10: Revenue | B10: ='Raw Data'!F4 -> 60680 | C10: =B10*(1+$B$5) -> 63714 | D10: =C10*(1+$B$5) -> 66899.7 | E10: =D10*(1+$B$5) -> 70244.685
A11: EBITDA | B11: ='Raw Data'!F5 -> 14289 | C11: =C10*$C$5 -> 15291.36 | D11: =D10*$C$5 -> 16055.928 | E11: =E10*$C$5 -> 16858.724
A12: PAT | B12: ='Raw Data'!F6 -> 10644 | C12: =C10*$D$5 -> 11149.95 | D12: =D10*$D$5 -> 11707.447 | E12: =E10*$D$5 -> 12292.82
A14: Bear Case Forecast
A15: Revenue | B15: ='Raw Data'!F4 -> 60680 | C15: =B15*(1+$B$4) -> 61893.6 | D15: =C15*(1+$B$4) -> 63131.472 | E15: =D15*(1+$B$4) -> 64394.101
A16: EBITDA | B16: ='Raw Data'!F5 -> 14289 | C16: =C15*$C$4 -> 13616.592 | D16: =D15*$C$4 -> 13888.924 | E16: =E15*$C$4 -> 14166.702
A17: PAT | B17: ='Raw Data'!F6 -> 10644 | C17: =C15*$D$4 -> 9902.976 | D17: =D15*$D$4 -> 10101.036 | E17: =E15*$D$4 -> 10303.056
A19: Bull Case Forecast
A20: Revenue | B20: ='Raw Data'!F4 -> 60680 | C20: =B20*(1+$B$6) -> 65534.4 | D20: =C20*(1+$B$6) -> 70777.152 | E20: =D20*(1+$B$6) -> 76439.324
A21: EBITDA | B21: ='Raw Data'!F5 -> 14289 | C21: =C20*$C$6 -> 16383.6 | D21: =D20*$C$6 -> 17694.288 | E21: =E20*$C$6 -> 19109.831
A22: PAT | B22: ='Raw Data'!F6 -> 10644 | C22: =C20*$D$6 -> 12123.864 | D22: =D20*$D$6 -> 13093.773 | E22: =E20*$D$6 -> 14141.275

Sheet Valuation Analysis
A1: HUL Multiples-Based Valuation
A3: FY2024-25 Financial Base
A4: PAT | B4: ='Raw Data'!F6 -> 10644
A5: EBITDA | B5: ='Raw Data'!F5 -> 14289
A6: Cash & Cash Equivalents | B6: ='Raw Data'!F16 -> 5947
A7: Lease Liabilities | B7: ='Raw Data'!F17+'Raw Data'!F18 -> 1537
A9: Valuation Assumptions
A10: P/E Multiple | B10: 50
A11: EV/EBITDA Multiple | B11: 30
A13: P/E Implied Equity Value | B13: =B4*B10 -> 532200
A14: Enterprise Value | B14: =B5*B11 -> 428670
A15: EV/EBITDA Implied Equity Value | B15: =B14+B6-B7 -> 433080
A16: Difference Between Methods | B16: =B13-B15 -> 99120
A18: P/E Sensitivity Analysis
A19: P/E Multiple | B19: 40 | C19: 45 | D19: 50 | E19: 55 | F19: 60
A20: Implied Equity Value | B20: =$B$4*B19 -> 425760 | C20: =$B$4*C19 -> 478980 | D20: =$B$4*D19 -> 532200 | E20: =$B$4*E19 -> 585420 | F20: =$B$4*F19 -> 638640
A22: Valuation Insight
A23: The implied equity value is highly sensitive to the selected P/E multiple, ranging from approximately ₹4.26 lakh Cr at 40x to ₹6.39 lakh Cr at 60x.

Sheet Insights
A1: HUL Financial Analysis – Key Insights
A3: Theme | B3: Observation | C3: Evidence | D3: Business Interpretation
A4: Growth | B4: Revenue grew steadily over the 5-year period, but recent growth has slowed. | C4: Revenue CAGR 7.57%; FY25 YoY growth only 1.85%. | D4: HUL has delivered long-term growth, but near-term topline momentum has moderated.
A5: Profitability | B5: EBITDA growth lagged revenue growth over the period. | C5: Revenue CAGR 7.57% vs EBITDA CAGR 5.99%; EBITDA margin fell from about 25.0% to 23.5%. | D5: This indicates some operating margin pressure despite revenue expansion.
A6: Net Profit | B6: PAT remained comparatively resilient. | C6: PAT CAGR 7.55% and PAT margin improved from 16.98% in FY24 to 17.54% in FY25. | D6: Bottom-line profitability recovered even though operating margin remained under pressure.
A7: Return on Capital | B7: ROCE weakened until FY24 but recovered strongly in FY25 | C7: ROCE: 113.0% → 107.8% → 101.9% → 96.3% → 108.2%. | D7: Capital efficiency remains very strong, with a notable recovery in the latest year.
A8: Working Capital | B8: HUL maintained a negative cash conversion cycle. | C8: CCC remained negative; FY25 approximately -40.5 days. | D8: A negative CCC indicates that HUL generally converts its operating cycle into cash before supplier payments become due, supporting efficient working-capital management.
A9: Leverage | B9: HUL operates with very low financial leverage. | C9: No conventional borrowings; Debt/Equity approximately 0.03x in FY25 using lease liabilities. | D9: Low leverage reduces financing risk and gives HUL a conservative balance-sheet position.
A10: DuPont Analysis | B10: Shareholder returns improved over the analysed period. | C10: ROE increased from 18.3% in FY22 to 21.3% in FY25, while Equity Multiplier increased from 1.43x to 1.55x. | D10: Stable margins combined with changes in asset utilisation and capital structure supported higher ROE.
A11: Forecast Outlook | B11: Base Case indicates moderate growth over the next three years. | C11: At 5% annual revenue growth, FY28 Revenue is projected at about ₹70,245 Cr and PAT at about ₹12,293 Cr. | D11: The outlook suggests steady growth, assuming HUL maintains current margins and operating conditions.
A12: Valuation | B12: HUL's implied value changes significantly depending on the valuation method used. | C12: 50x P/E gives about ₹5.32 lakh Cr, while 30x EV/EBITDA gives about ₹4.33 lakh Cr equity value. | D12: Valuation is sensitive to assumptions and multiples, so multiple methods should be considered together.

Sheet Dashboard
A1: Hindustan Unilever Limited
A2: 5-Year Financial Performance Dashboard | FY2020-21 to FY2024-25
A4: Revenue | D4: EBITDA Margin | G4: PAT | J4: ROCE
A5: =TEXT('Raw Data'!F4,"₹#,##0")&" Cr" -> ₹60,680 Cr | D5: =Ratios!F8 -> 0.23548121 | G5: =TEXT('Raw Data'!F6,"₹#,##0")&" Cr" -> ₹10,644 Cr | J5: =Ratios!F16 -> 1.082
A34: Key Takeways
A36: Growth | E36: Profitability | I36: Efficiency
A37: Revenue CAGR: 7.57% FY25 revenue growth slowed to 1.85% | E37: FY25 EBITDA Margin: 23.55% Margin declined from ~25.0% in FY21. | I37: FY25 CCC: -40.5 Days Negative CCC reflects strong working-capital efficiency.
A59: Advanced Financial Analysis
A62: FY25 DuPont ROE | D62: FY28 Base Revenue | G62: FY28 Base PAT | J62: P/E Implied Equity Value
A63: ='DuPont Analysis'!F8 -> 0.21261211 | D63: ='Forecast & Scenario'!E10 -> 70244.685 | G63: ='Forecast & Scenario'!E12 -> 12292.82 | J63: ='Valuation Analysis'!B13 -> 532200
A89: Management Insights
A91: 1. Growth: HUL delivered ~7.6% revenue CAGR over FY21-FY25, although recent revenue growth has moderated.
A94: 2. Profitability: PAT margin remained resilient near 17%-18%, while EBITDA margin softened from about 25.0% to 23.5%.
A97: 3. Outlook: Under the Base Case, revenue is projected to reach approximately ₹70,245 Cr by FY2027-28, while Bear and Bull scenarios highlight the range of possible outcomes.
